apacepy/__init__.py
apacepy/calibration.py
apacepy/calibration_support.py
apacepy/control.py
apacepy/econ_eval.py
apacepy/epidemic.py
apacepy/features_conditions.py
apacepy/history.py
apacepy/inputs.py
apacepy/model_objects.py
apacepy/multi_epidemics.py
apacepy/scenario_simulation.py
apacepy/sim_events.py
apacepy/support.py
apacepy/time_series.py
apacepy/transmission.py
apacepy/analysis/scenarios.py
apacepy/analysis/trajectories.py
apacepy/analysis/visualize_scenarios.py
apacepy-1.1.4.dist-info/licenses/LICENSE
apacepy-1.1.4.dist-info/METADATA
apacepy-1.1.4.dist-info/WHEEL
apacepy-1.1.4.dist-info/top_level.txt
apacepy-1.1.4.dist-info/RECORD
