Metadata-Version: 2.4
Name: apacepy
Version: 1.1.4
Summary: Analytical Platform for Adaptive Control of Epidemics (APACE)
Home-page: https://github.com/yaesoubilab/apacepy
Author: Reza Yaesoubi
Author-email: reza.yaesoubi@yale.edu
License: MIT License
License-File: LICENSE
Requires-Dist: numpy
Requires-Dist: matplotlib
Requires-Dist: scipy
Requires-Dist: deampy
Requires-Dist: statsmodels
Requires-Dist: scikit-learn
Dynamic: author
Dynamic: author-email
Dynamic: description
Dynamic: home-page
Dynamic: license
Dynamic: license-file
Dynamic: requires-dist
Dynamic: summary
